Metadata-Version: 2.1
Name: rsconnect_python
Version: 1.28.2
Summary: The Posit Connect command-line interface.
Author-email: "Posit, PBC" <rsconnect@posit.co>
License: # MIT License
Project-URL: Repository, http://github.com/posit-dev/rsconnect-python
Project-URL: Documentation, https://docs.posit.co/rsconnect-python
Requires-Python: >=3.8
License-File: LICENSE.md
Requires-Dist: typing-extensions>=4.8.0
Requires-Dist: pip>=10.0.0
Requires-Dist: semver<4.0.0,>=2.0.0
Requires-Dist: pyjwt>=2.4.0
Requires-Dist: click>=8.0.0
Requires-Dist: toml>=0.10; python_version < "3.11"
Provides-Extra: docs
Requires-Dist: mkdocs-material; extra == "docs"
Requires-Dist: mkdocs-click; extra == "docs"
Requires-Dist: pymdown-extensions; extra == "docs"
Requires-Dist: mkdocs-macros-plugin; extra == "docs"
Provides-Extra: mcp
Requires-Dist: fastmcp==2.12.4; python_version >= "3.10" and extra == "mcp"
Provides-Extra: snowflake
Requires-Dist: snowflake-cli; extra == "snowflake"
Provides-Extra: test
Requires-Dist: black==24.3.0; extra == "test"
Requires-Dist: coverage; extra == "test"
Requires-Dist: flake8-pyproject; extra == "test"
Requires-Dist: flake8; extra == "test"
Requires-Dist: httpretty; extra == "test"
Requires-Dist: ipykernel; extra == "test"
Requires-Dist: nbconvert; extra == "test"
Requires-Dist: pyright; extra == "test"
Requires-Dist: pytest-cov; extra == "test"
Requires-Dist: pytest; extra == "test"
Requires-Dist: setuptools>=61; extra == "test"
Requires-Dist: setuptools-scm[toml]>=3.4; extra == "test"
Requires-Dist: twine; extra == "test"
Requires-Dist: types-Flask; extra == "test"
Requires-Dist: fastmcp==2.12.4; python_version >= "3.10" and extra == "test"
